github_poetry_starter/__init__.py
github_poetry_starter-0.4.0.dist-info/LICENSE
github_poetry_starter-0.4.0.dist-info/WHEEL
github_poetry_starter-0.4.0.dist-info/METADATA
github_poetry_starter-0.4.0.dist-info/RECORD
