Metadata-Version: 2.1
Name: github-poetry-starter
Version: 0.4.0
Summary: GitHub Actions starter for python with python-poetry
Author: hexatester
Author-email: hexatester@protonmail.com
Requires-Python: >=3.6.1,<4.0.0
Classifier: Programming Language :: Python :: 3
Classifier: Programming Language :: Python :: 3.7
Classifier: Programming Language :: Python :: 3.8
Classifier: Programming Language :: Python :: 3.9
